{
  "shelters": [
    {
      "id": "1",
      "name": "Refugio de Animales San Francisco",
      "type": "refugio",
      "description": "Un refugio dedicado al cuidado y protección de animales abandonados.",
      "contact": {
        "email": "contacto@refugiosanfrancisco.com",
        "phone": "+54 351 123-4567",
        "website": "https://refugiosanfrancisco.com",
        "socialMedia": {
          "facebook": "https://facebook.com/refugiosanfrancisco",
          "instagram": "https://instagram.com/refugiosanfrancisco"
        }
      },
      "location": {
        "address": "Av. San Martín 1234",
        "city": "Córdoba",
        "state": "Córdoba",
        "country": "Argentina",
        "coordinates": {
          "latitude": -31.4201,
          "longitude": -64.1888
        }
      },
      "capacity": {
        "total": 100,
        "current": 50,
        "available": 50
      },
      "facilities": {
        "indoor": true,
        "outdoor": true,
        "medical": true,
        "training": true,
        "description": "Área de cuarentena, Clínica veterinaria, Patio de juegos"
      },
      "services": [
        "Adopción de mascotas",
        "Esterilización",
        "Vacunación",
        "Cuidado temporal"
      ],
      "staff": {
        "total": 15,
        "volunteers": 10,
        "roles": ["veterinario", "cuidador", "voluntario"]
      },
      "animals": {
        "total": 50,
        "byType": {
          "perros": 30,
          "gatos": 20
        }
      },
      "photos": [
        "https://images.unsplash.com/photo-1601758228041-f3b2795255f1?w=800&auto=format&fit=crop&q=60",
        "https://images.unsplash.com/photo-1601979031925-42453c73fcd6?w=800&auto=format&fit=crop&q=60",
        "https://images.unsplash.com/photo-1601758124510-52d02ddb7cbd?w=800&auto=format&fit=crop&q=60"
      ],
      "status": "active",
      "registrationDate": "2023-01-01T00:00:00Z",
      "lastUpdate": "2023-12-31T00:00:00Z"
    },
    {
      "id": "2",
      "name": "Hogar de Mascotas",
      "type": "refugio",
      "description": "Centro de rescate especializado en perros y gatos, con programas de rehabilitación y socialización.",
      "contact": {
        "email": "contacto@hogardemascotas.com",
        "phone": "+54 351 987-6543",
        "website": "www.hogardemascotas.com",
        "socialMedia": {
          "facebook": "hogardemascotas",
          "instagram": "@hogardemascotas",
          "twitter": "@hogardemascotas"
        }
      },
      "location": {
        "address": "Calle San Martín 567",
        "city": "Córdoba",
        "state": "Córdoba",
        "country": "Argentina",
        "coordinates": {
          "latitude": -31.4201,
          "longitude": -64.1888
        }
      },
      "capacity": {
        "total": 40,
        "current": 28,
        "available": 12
      },
      "facilities": {
        "indoor": true,
        "outdoor": true,
        "medical": true,
        "training": true,
        "description": "Área de rehabilitación, Clínica veterinaria, Patio de juegos"
      },
      "services": [
        "Adopción",
        "Esterilización",
        "Vacunación",
        "Microchip",
        "Cuidado temporal",
        "Rehabilitación"
      ],
      "staff": {
        "total": 12,
        "volunteers": 8,
        "roles": ["veterinario", "cuidador", "voluntario"]
      },
      "animals": {
        "total": 28,
        "byType": {
          "perros": 18,
          "gatos": 10
        }
      },
      "photos": [
        "https://images.unsplash.com/photo-1544568100-847a948585b9?w=800&auto=format&fit=crop&q=60",
        "https://images.unsplash.com/photo-1548199973-03cce0bbc87b?w=800&auto=format&fit=crop&q=60",
        "https://images.unsplash.com/photo-1583511655857-d19b40a7a54e?w=800&auto=format&fit=crop&q=60"
      ],
      "status": "active",
      "registrationDate": "2018-07-22T00:00:00Z",
      "lastUpdate": "2023-12-31T00:00:00Z"
    },
    {
      "id": "R003",
      "name": "Amigos Peludos",
      "description": "Refugio especializado en perros de todas las edades, con énfasis en rehabilitación de animales maltratados.",
      "status": "active",
      "address": {
        "street": "Av. Corrientes 2345",
        "city": "Rosario",
        "province": "Santa Fe",
        "postalCode": "S2000",
        "country": "Argentina"
      },
      "contact": {
        "phone": "+54 341 234-5678",
        "email": "info@amigospeludos.org",
        "website": "www.amigospeludos.org",
        "socialMedia": {
          "facebook": "amigospeludos",
          "instagram": "@amigospeludos",
          "twitter": "@amigospeludos"
        }
      },
      "openingHours": {
        "monday": "09:00 - 19:00",
        "tuesday": "09:00 - 19:00",
        "wednesday": "09:00 - 19:00",
        "thursday": "09:00 - 19:00",
        "friday": "09:00 - 19:00",
        "saturday": "10:00 - 16:00",
        "sunday": "10:00 - 14:00"
      },
      "capacity": {
        "max": 60,
        "current": 45
      },
      "services": [
        "Adopción",
        "Esterilización",
        "Vacunación",
        "Microchip",
        "Rehabilitación",
        "Entrenamiento básico"
      ],
      "adoptionRequirements": [
        "Mayor de 18 años",
        "Documento de identidad",
        "Comprobante de domicilio",
        "Entrevista previa",
        "Firma de contrato de adopción",
        "Visita domiciliaria"
      ],
      "statistics": {
        "successfulAdoptions": 950,
        "rescuedAnimals": 1800,
        "sterilizedAnimals": 2200
      },
      "photos": [
        "https://images.unsplash.com/photo-1548199973-03cce0bbc87b?w=800&auto=format&fit=crop&q=60",
        "https://images.unsplash.com/photo-1548199973-03cce0bbc87b?w=800&auto=format&fit=crop&q=60",
        "https://images.unsplash.com/photo-1548199973-03cce0bbc87b?w=800&auto=format&fit=crop&q=60"
      ],
      "reviews": {
        "rating": 4.7,
        "count": 120
      },
      "createdAt": "2017-05-10",
      "updatedAt": "2017-05-10"
    },
    {
      "id": "R004",
      "name": "Gatitos Felices",
      "description": "Refugio especializado en gatos, con programas de socialización y cuidado especial para felinos.",
      "status": "active",
      "address": {
        "street": "Calle Sarmiento 789",
        "city": "Mendoza",
        "province": "Mendoza",
        "postalCode": "M5500",
        "country": "Argentina"
      },
      "contact": {
        "phone": "+54 261 345-6789",
        "email": "info@gatitosfelices.org",
        "website": "www.gatitosfelices.org",
        "socialMedia": {
          "facebook": "gatitosfelices",
          "instagram": "@gatitosfelices",
          "twitter": "@gatitosfelices"
        }
      },
      "openingHours": {
        "monday": "10:00 - 18:00",
        "tuesday": "10:00 - 18:00",
        "wednesday": "10:00 - 18:00",
        "thursday": "10:00 - 18:00",
        "friday": "10:00 - 18:00",
        "saturday": "10:00 - 14:00",
        "sunday": "Cerrado"
      },
      "capacity": {
        "max": 40,
        "current": 32
      },
      "services": [
        "Adopción",
        "Esterilización",
        "Vacunación",
        "Microchip",
        "Cuidado especial para gatos",
        "Socialización"
      ],
      "adoptionRequirements": [
        "Mayor de 21 años",
        "Documento de identidad",
        "Comprobante de domicilio",
        "Entrevista previa",
        "Firma de contrato de adopción",
        "Compromiso de esterilización"
      ],
      "statistics": {
        "successfulAdoptions": 700,
        "rescuedAnimals": 1200,
        "sterilizedAnimals": 1500
      },
      "photos": [
        "https://images.unsplash.com/photo-1514888286974-6c03e2ca1dba?w=800&auto=format&fit=crop&q=60",
        "https://images.unsplash.com/photo-1514888286974-6c03e2ca1dba?w=800&auto=format&fit=crop&q=60",
        "https://images.unsplash.com/photo-1514888286974-6c03e2ca1dba?w=800&auto=format&fit=crop&q=60"
      ],
      "reviews": {
        "rating": 4.9,
        "count": 85
      },
      "createdAt": "2019-02-20",
      "updatedAt": "2019-02-20"
    },
    {
      "id": "R005",
      "name": "Refugio del Sur",
      "description": "Centro de rescate y rehabilitación para animales de todas las especies, con énfasis en educación comunitaria.",
      "status": "active",
      "address": {
        "street": "Av. San Martín 123",
        "city": "Bahía Blanca",
        "province": "Buenos Aires",
        "postalCode": "B8000",
        "country": "Argentina"
      },
      "contact": {
        "phone": "+54 291 456-7890",
        "email": "info@refugiodelsur.org",
        "website": "www.refugiodelsur.org",
        "socialMedia": {
          "facebook": "refugiodelsur",
          "instagram": "@refugiodelsur",
          "twitter": "@refugiodelsur"
        }
      },
      "openingHours": {
        "monday": "08:00 - 20:00",
        "tuesday": "08:00 - 20:00",
        "wednesday": "08:00 - 20:00",
        "thursday": "08:00 - 20:00",
        "friday": "08:00 - 20:00",
        "saturday": "09:00 - 18:00",
        "sunday": "09:00 - 14:00"
      },
      "capacity": {
        "max": 100,
        "current": 75
      },
      "services": [
        "Adopción",
        "Esterilización",
        "Vacunación",
        "Microchip",
        "Rehabilitación",
        "Educación comunitaria",
        "Voluntariado"
      ],
      "adoptionRequirements": [
        "Mayor de 18 años",
        "Documento de identidad",
        "Comprobante de domicilio",
        "Entrevista previa",
        "Firma de contrato de adopción",
        "Visita domiciliaria",
        "Curso de tenencia responsable"
      ],
      "statistics": {
        "successfulAdoptions": 1500,
        "rescuedAnimals": 3000,
        "sterilizedAnimals": 3500
      },
      "photos": [
        "https://images.unsplash.com/photo-1552053831-71594a27632d?w=800&auto=format&fit=crop&q=60",
        "https://images.unsplash.com/photo-1552053831-71594a27632d?w=800&auto=format&fit=crop&q=60",
        "https://images.unsplash.com/photo-1552053831-71594a27632d?w=800&auto=format&fit=crop&q=60"
      ],
      "reviews": {
        "rating": 4.8,
        "count": 200
      },
      "createdAt": "2016-08-15",
      "updatedAt": "2016-08-15"
    },
    {
      "id": "R006",
      "name": "Huellas de Amor",
      "description": "Refugio especializado en perros de razas grandes y especiales, con programas de entrenamiento avanzado.",
      "status": "active",
      "address": {
        "street": "Calle Belgrano 456",
        "city": "Tucumán",
        "province": "Tucumán",
        "postalCode": "T4000",
        "country": "Argentina"
      },
      "contact": {
        "phone": "+54 381 567-8901",
        "email": "info@huellasdeamor.org",
        "website": "www.huellasdeamor.org",
        "socialMedia": {
          "facebook": "huellasdeamor",
          "instagram": "@huellasdeamor",
          "twitter": "@huellasdeamor"
        }
      },
      "openingHours": {
        "monday": "09:00 - 18:00",
        "tuesday": "09:00 - 18:00",
        "wednesday": "09:00 - 18:00",
        "thursday": "09:00 - 18:00",
        "friday": "09:00 - 18:00",
        "saturday": "10:00 - 15:00",
        "sunday": "Cerrado"
      },
      "capacity": {
        "max": 45,
        "current": 38
      },
      "services": [
        "Adopción",
        "Esterilización",
        "Vacunación",
        "Microchip",
        "Entrenamiento avanzado",
        "Rehabilitación",
        "Terapia asistida"
      ],
      "adoptionRequirements": [
        "Mayor de 25 años",
        "Documento de identidad",
        "Comprobante de domicilio",
        "Entrevista previa",
        "Firma de contrato de adopción",
        "Visita domiciliaria",
        "Curso de manejo de razas grandes"
      ],
      "statistics": {
        "successfulAdoptions": 600,
        "rescuedAnimals": 1000,
        "sterilizedAnimals": 1200
      },
      "photos": [
        "https://images.unsplash.com/photo-1583511655857-d19b40a7a54e?w=800&auto=format&fit=crop&q=60",
        "https://images.unsplash.com/photo-1583511655857-d19b40a7a54e?w=800&auto=format&fit=crop&q=60",
        "https://images.unsplash.com/photo-1583511655857-d19b40a7a54e?w=800&auto=format&fit=crop&q=60"
      ],
      "reviews": {
        "rating": 4.7,
        "count": 95
      },
      "createdAt": "2018-11-30",
      "updatedAt": "2018-11-30"
    },
    {
      "id": "R007",
      "name": "Refugio del Norte",
      "description": "Centro integral de rescate y cuidado animal, con programas de voluntariado y educación ambiental.",
      "status": "active",
      "address": {
        "street": "Av. 9 de Julio 789",
        "city": "Salta",
        "province": "Salta",
        "postalCode": "A4400",
        "country": "Argentina"
      },
      "contact": {
        "phone": "+54 387 678-9012",
        "email": "info@refugiodelnorte.org",
        "website": "www.refugiodelnorte.org",
        "socialMedia": {
          "facebook": "refugiodelnorte",
          "instagram": "@refugiodelnorte",
          "twitter": "@refugiodelnorte"
        }
      },
      "openingHours": {
        "monday": "08:00 - 19:00",
        "tuesday": "08:00 - 19:00",
        "wednesday": "08:00 - 19:00",
        "thursday": "08:00 - 19:00",
        "friday": "08:00 - 19:00",
        "saturday": "09:00 - 17:00",
        "sunday": "09:00 - 13:00"
      },
      "capacity": {
        "max": 80,
        "current": 65
      },
      "services": [
        "Adopción",
        "Esterilización",
        "Vacunación",
        "Microchip",
        "Rehabilitación",
        "Educación ambiental",
        "Voluntariado",
        "Cuidado de fauna silvestre"
      ],
      "adoptionRequirements": [
        "Mayor de 18 años",
        "Documento de identidad",
        "Comprobante de domicilio",
        "Entrevista previa",
        "Firma de contrato de adopción",
        "Visita domiciliaria",
        "Curso de tenencia responsable"
      ],
      "statistics": {
        "successfulAdoptions": 1100,
        "rescuedAnimals": 2200,
        "sterilizedAnimals": 2800
      },
      "photos": [
        "https://images.unsplash.com/photo-1552053831-71594a27632d?w=800&auto=format&fit=crop&q=60",
        "https://images.unsplash.com/photo-1548199973-03cce0bbc87b?w=800&auto=format&fit=crop&q=60",
        "https://images.unsplash.com/photo-1514888286974-6c03e2ca1dba?w=800&auto=format&fit=crop&q=60"
      ],
      "reviews": {
        "rating": 4.9,
        "count": 150
      },
      "createdAt": "2017-04-05",
      "updatedAt": "2017-04-05"
    }
  ]
} 